cli_args/__init__.py
cli_args-1.1.0.dist-info/LICENSE
cli_args-1.1.0.dist-info/METADATA
cli_args-1.1.0.dist-info/WHEEL
cli_args-1.1.0.dist-info/top_level.txt
cli_args-1.1.0.dist-info/RECORD
