Metadata-Version: 2.1
Name: cli-args
Version: 1.1.0
Summary: Command line arguments. Made simple.
Home-page: UNKNOWN
License: MIT
Platform: UNKNOWN
Requires-Dist: argparse
